routilux/__init__.py
routilux/connection.py
routilux/error_handler.py
routilux/event.py
routilux/execution_tracker.py
routilux/flow.py
routilux/job_state.py
routilux/routine.py
routilux/slot.py
routilux/builtin_routines/__init__.py
routilux/builtin_routines/control_flow/__init__.py
routilux/builtin_routines/control_flow/conditional_router.py
routilux/builtin_routines/data_processing/__init__.py
routilux/builtin_routines/data_processing/data_transformer.py
routilux/builtin_routines/data_processing/data_validator.py
routilux/builtin_routines/text_processing/__init__.py
routilux/builtin_routines/text_processing/result_extractor.py
routilux/builtin_routines/text_processing/text_clipper.py
routilux/builtin_routines/text_processing/text_renderer.py
routilux/builtin_routines/utils/__init__.py
routilux/builtin_routines/utils/data_flattener.py
routilux/builtin_routines/utils/time_provider.py
routilux-0.9.0.dist-info/licenses/LICENSE
scripts/generate_release_notes.py
tools/analyze_codebase_ast.py
routilux-0.9.0.dist-info/METADATA
routilux-0.9.0.dist-info/WHEEL
routilux-0.9.0.dist-info/top_level.txt
routilux-0.9.0.dist-info/RECORD
